iot/ftps/client/__init__.py
iot/ftps/client/_client.py
iot/ftps/client/_version.py
iot_ftps_client-1.1.1.dist-info/METADATA
iot_ftps_client-1.1.1.dist-info/WHEEL
iot_ftps_client-1.1.1.dist-info/top_level.txt
iot_ftps_client-1.1.1.dist-info/RECORD
