Metadata-Version: 2.1
Name: iot-ftps-client
Version: 1.1.1
Summary: IoT FTPS Client Library for Python
Author: Dylan Gonzales
Author-email: py.iot.utils@gmail.com
License: MIT License
Classifier: Programming Language :: Python :: 3 :: Only
Classifier: Programming Language :: Python :: 3
Classifier: Programming Language :: Python :: 3.7
Classifier: Programming Language :: Python :: 3.8
Classifier: Programming Language :: Python :: 3.9
Classifier: Programming Language :: Python :: 3.10
Classifier: License :: OSI Approved :: MIT License
Requires-Python: >=3.7
Requires-Dist: pydantic (==1.9.0)
